PhyREC/ImageSequence.py
PhyREC/PlotWaves.py
PhyREC/SignalAnalysis.py
PhyREC/SignalProcess.py
PhyREC/SupportFunctions.py
PhyREC/__init__.py
PhyREC/_version.py
phyrec-0.7.0.dist-info/METADATA
phyrec-0.7.0.dist-info/WHEEL
phyrec-0.7.0.dist-info/top_level.txt
phyrec-0.7.0.dist-info/RECORD
