Metadata-Version: 2.2
Name: PhyREC
Version: 0.7.0
Summary: Library for electrophysiological analysis based on neo
Author-email: Anton Guimerà Brunet <anton.guimera@csic.es>
License: GPL-3.0-or-later
Project-URL: Homepage, https://github.com/aguimera/PhyREC
Classifier: Development Status :: 3 - Alpha
Classifier: Intended Audience :: Science/Research
Classifier: Programming Language :: Python :: 3.7
Classifier: Topic :: Scientific/Engineering
Requires-Python: >=3.7
Requires-Dist: quantities~=0.16.0
Requires-Dist: matplotlib~=3.0
Requires-Dist: numpy~=2.0
Requires-Dist: neo~=0.14.0
Requires-Dist: pandas~=2.0
Requires-Dist: scipy~=1.0
Requires-Dist: PyGFETdb~=0.7.0
Requires-Dist: seaborn~=0.13.0
Requires-Dist: tsdownsample~=0.1.0
